flymyai/__init__.py
flymyai/core/__init__.py
flymyai/core/_response.py
flymyai/core/_streaming.py
flymyai/core/authorizations.py
flymyai/core/client.py
flymyai/core/clients/AsyncClient.py
flymyai/core/clients/SyncClient.py
flymyai/core/clients/__init__.py
flymyai/core/clients/base_client.py
flymyai/core/clients/base_m1_client.py
flymyai/core/clients/m1AsyncClient.py
flymyai/core/clients/m1Client.py
flymyai/core/exceptions.py
flymyai/core/models/__init__.py
flymyai/core/models/base.py
flymyai/core/models/error_responses.py
flymyai/core/models/m1_history.py
flymyai/core/models/successful_responses.py
flymyai/core/response_factory/__init__.py
flymyai/core/response_factory/async_task_result_factory.py
flymyai/core/response_factory/base_response_factory.py
flymyai/core/response_factory/plain_inference_response_factory.py
flymyai/core/stream_iterators/AsyncPredictionStream.py
flymyai/core/stream_iterators/PredictionStream.py
flymyai/core/stream_iterators/__init__.py
flymyai/core/stream_iterators/exceptions.py
flymyai/core/types/__init__.py
flymyai/core/types/event_types.py
flymyai/core/types/m1.py
flymyai/multipart/__init__.py
flymyai/multipart/base_field.py
flymyai/multipart/binary_field.py
flymyai/multipart/payload.py
flymyai/multipart/simple_field.py
flymyai/utils/__init__.py
flymyai/utils/utils.py
flymyai-1.0.25.dist-info/LICENSE
flymyai-1.0.25.dist-info/METADATA
flymyai-1.0.25.dist-info/WHEEL
flymyai-1.0.25.dist-info/RECORD
