Metadata-Version: 2.3
Name: flymyai
Version: 1.0.25
Summary: 
Author: denti
Author-email: dentiwork@yandex.ru
Requires-Python: >=3.8
Classifier: Programming Language :: Python :: 3
Classifier: Programming Language :: Python :: 3.8
Classifier: Programming Language :: Python :: 3.9
Classifier: Programming Language :: Python :: 3.10
Classifier: Programming Language :: Python :: 3.11
Classifier: Programming Language :: Python :: 3.12
Classifier: Programming Language :: Python :: 3.13
Requires-Dist: httpx[http2] (>=0.26.0)
Requires-Dist: pydantic (>=2.0.0)
Requires-Dist: setuptools (>69.1.1)
Requires-Dist: typing-extensions (>=4.9.0)
